HISTORY.rst
LICENSE
MANIFEST.in
README.md
requirements.txt
setup.py
django_channels_jwt_auth_middleware/__init__.py
django_channels_jwt_auth_middleware/auth.py
django_channels_jwt_auth_middleware.egg-info/PKG-INFO
django_channels_jwt_auth_middleware.egg-info/SOURCES.txt
django_channels_jwt_auth_middleware.egg-info/dependency_links.txt
django_channels_jwt_auth_middleware.egg-info/not-zip-safe
django_channels_jwt_auth_middleware.egg-info/requires.txt
django_channels_jwt_auth_middleware.egg-info/top_level.txt