Metadata-Version: 2.1
Name: django-channels-jwt-auth-middleware
Version: 1.0.0
Summary: JWT Auth Middleware for Django Channels
Home-page: https://github.com/joshua-hashimoto/django-channels-jwt-auth-middleware
Author: Joshua Hashimoto
Author-email: onandgo.dev@gmail.com
License: MIT
Keywords: django_channels_jwt_auth_middleware
Platform: UNKNOWN
Classifier: Development Status :: 5 - Production/Stable
Classifier: Intended Audience :: Developers
Classifier: License :: OSI Approved :: MIT License
Classifier: Natural Language :: English
Classifier: Programming Language :: Python :: 3.8
Requires-Python: >=3.8
